libskynet/__init__.py
libskynet/libgcc_s_seh-1.dll
libskynet/libgfortran-3.dll
libskynet/libopenblas.dll
libskynet/libquadmath-0.dll
libskynet/libskynet.dll
libskynet/libskynet.so
libskynet/snBase.py
libskynet/snNet.py
libskynet/snOperator.py
libskynet/snResNet50.py
libskynet/snType.py
libskynet/snWeight.py
libskynet-1.0.4.dist-info/LICENSE
libskynet-1.0.4.dist-info/METADATA
libskynet-1.0.4.dist-info/WHEEL
libskynet-1.0.4.dist-info/top_level.txt
libskynet-1.0.4.dist-info/RECORD
